docs/__init__.py
docs/conf.py
docs/settings.py
mmpy_bot_mk2/__init__.py
mmpy_bot_mk2/bot.py
mmpy_bot_mk2/driver.py
mmpy_bot_mk2/event_handler.py
mmpy_bot_mk2/exceptions.py
mmpy_bot_mk2/function.py
mmpy_bot_mk2/scheduler.py
mmpy_bot_mk2/settings.py
mmpy_bot_mk2/threadpool.py
mmpy_bot_mk2/utils.py
mmpy_bot_mk2/version.txt
mmpy_bot_mk2/webhook_server.py
mmpy_bot_mk2/wrappers.py
mmpy_bot_mk2/plugins/__init__.py
mmpy_bot_mk2/plugins/base.py
mmpy_bot_mk2/plugins/example.py
mmpy_bot_mk2/plugins/help_example.py
mmpy_bot_mk2/plugins/webhook_example.py
mmpy_bot_mk2-2.1.6.dist-info/AUTHORS.rst
mmpy_bot_mk2-2.1.6.dist-info/LICENSE
mmpy_bot_mk2-2.1.6.dist-info/METADATA
mmpy_bot_mk2-2.1.6.dist-info/WHEEL
mmpy_bot_mk2-2.1.6.dist-info/entry_points.txt
mmpy_bot_mk2-2.1.6.dist-info/top_level.txt
mmpy_bot_mk2-2.1.6.dist-info/RECORD
