Metadata-Version: 2.1
Name: mmpy-bot-mk2
Version: 2.1.6
Summary: A python based bot for Mattermost with its own webhook server.
Home-page: https://github.com/movax01h/mmpy_bot_mk2
Author: Alex Tzonkov
Author-email: anton.ohontsev@gmail.com
License: MIT
Keywords: chat bot mattermost
Platform: Any
Classifier: Development Status :: 5 - Production/Stable
Classifier: License :: OSI Approved :: MIT License
Classifier: Intended Audience :: Developers
Classifier: Operating System :: OS Independent
Classifier: Programming Language :: Python :: 3.8
Classifier: Programming Language :: Python :: 3.9
Classifier: Programming Language :: Python :: 3.10
Classifier: Topic :: Internet :: WWW/HTTP
Classifier: Topic :: Software Development :: Libraries :: Python Modules
Requires-Python: >=3.8
License-File: LICENSE
License-File: AUTHORS.rst
Requires-Dist: aiohttp >=3.7.4.post0
Requires-Dist: click >=7.0
Requires-Dist: mattermostautodriver ~=1.3.0
Requires-Dist: schedule >=0.6.0
Provides-Extra: dev
Requires-Dist: black ==24.2.0 ; extra == 'dev'
Requires-Dist: docformatter ==1.7.5 ; extra == 'dev'
Requires-Dist: filelock ==3.13.1 ; extra == 'dev'
Requires-Dist: isort ==5.13.2 ; extra == 'dev'
Requires-Dist: flake8 ==7.0.0 ; extra == 'dev'
Requires-Dist: pytest ==8.0.1 ; extra == 'dev'
Requires-Dist: pytest-xdist ==3.5.0 ; extra == 'dev'
Requires-Dist: pytype ==2024.2.13 ; extra == 'dev'
Requires-Dist: snapshottest ==0.6.0 ; extra == 'dev'
Requires-Dist: wheel ==0.42.0 ; extra == 'dev'
